InstagramGrabber/__init__.py
InstagramGrabber/__main__.py
InstagramGrabber/exceptions.py
InstagramGrabber/helper.py
InstagramGrabber/media.py
InstagramGrabber/request.py
InstagramGrabber/version.py
InstagramGrabber/post/__init__.py
InstagramGrabber/post/__main__.py
InstagramGrabber/user/__init__.py
InstagramGrabber/user/__main__.py
InstagramGrabber/user/posts.py
InstagramGrabber/user/reels.py
InstagramGrabber/user/stories.py
InstagramGrabber-2.0.0.dist-info/LICENSE
InstagramGrabber-2.0.0.dist-info/METADATA
InstagramGrabber-2.0.0.dist-info/WHEEL
InstagramGrabber-2.0.0.dist-info/top_level.txt
InstagramGrabber-2.0.0.dist-info/RECORD
