Metadata-Version: 2.1
Name: InstagramGrabber
Version: 2.0.0
Summary: Simple project to grab instagram info
Home-page: https://github.com/sukundev/instagramgrabber
Author: SukunDev
Author-email: sukundev32@gmail.com
License: The Unlicense (Unlicense)
Keywords: instagram,instagram-grabber,instagram grabber,python3,api,instagram api
Classifier: Development Status :: 4 - Beta
Classifier: Intended Audience :: Developers
Classifier: License :: OSI Approved :: The Unlicense (Unlicense)
Classifier: Programming Language :: Python :: 3.7
Classifier: Programming Language :: Python :: 3.8
Classifier: Programming Language :: Python :: 3.9
Classifier: Programming Language :: Python :: 3.11
Classifier: Programming Language :: Python
Classifier: Topic :: Internet
Classifier: Topic :: Multimedia :: Video
Classifier: Topic :: Software Development :: Libraries :: Python Modules
Classifier: Topic :: Utilities
Requires-Python: >=3.7
License-File: LICENSE
Requires-Dist: requests
